iflow_mcp_call518_mcp_postgresql_ops-0.0.0.dist-info/licenses/LICENSE
mcp_postgresql_ops/__init__.py
mcp_postgresql_ops/__main__.py
mcp_postgresql_ops/functions.py
mcp_postgresql_ops/mcp_main.py
mcp_postgresql_ops/version_compat.py
iflow_mcp_call518_mcp_postgresql_ops-0.0.0.dist-info/METADATA
iflow_mcp_call518_mcp_postgresql_ops-0.0.0.dist-info/WHEEL
iflow_mcp_call518_mcp_postgresql_ops-0.0.0.dist-info/entry_points.txt
iflow_mcp_call518_mcp_postgresql_ops-0.0.0.dist-info/top_level.txt
iflow_mcp_call518_mcp_postgresql_ops-0.0.0.dist-info/RECORD
