Metadata-Version: 2.4
Name: iflow-mcp_call518_mcp-postgresql-ops
Version: 0.0.0
Summary: Add your description here
Author-email: JungJungIn <call518@gmail.com>
Requires-Python: >=3.12
License-File: LICENSE
Requires-Dist: fastmcp>=2.12.3
Requires-Dist: asyncpg>=0.29.0
Requires-Dist: psycopg2-binary>=2.9.7
Provides-Extra: dev
Requires-Dist: pytest>=7.0.0; extra == "dev"
Requires-Dist: pytest-asyncio>=0.21.0; extra == "dev"
Dynamic: license-file
